pixascii/__init__.py
pixascii/cli.py
pixascii-0.1.3.dist-info/entry_points.txt
pixascii-0.1.3.dist-info/licenses/LICENSE
pixascii-0.1.3.dist-info/WHEEL
pixascii-0.1.3.dist-info/METADATA
pixascii-0.1.3.dist-info/RECORD
