Metadata-Version: 2.4
Name: pixascii
Version: 0.1.3
Summary: Convert images to ASCII art
Author-email: Henri <hent32421@gmail.com>
License-Expression: MIT
License-File: LICENSE
Project-URL: Homepage, https://github.com/hent83722/pixascii
